deepaugment/__init__.py
deepaugment/augmenter.py
deepaugment/build_features.py
deepaugment/childcnn.py
deepaugment/controller.py
deepaugment/deepaugment.py
deepaugment/image_generator.py
deepaugment/notebook.py
deepaugment/objective.py
deepaugment/run.py
deepaugment/run_full_model.py
deepaugment/wide_res_net.py
deepaugment/lib/__init__.py
deepaugment/lib/cutout.py
deepaugment/lib/decorators.py
deepaugment/lib/helpers.py
deepaugment/lib/pandas_utilities.py
deepaugment-1.1.2.dist-info/LICENSE
deepaugment-1.1.2.dist-info/METADATA
deepaugment-1.1.2.dist-info/WHEEL
deepaugment-1.1.2.dist-info/top_level.txt
deepaugment-1.1.2.dist-info/RECORD
