Metadata-Version: 2.1
Name: deepaugment
Version: 1.1.2
Summary: Discover augmentation strategies tailored for your data
Home-page: https://github.com/barisozmen/deepaugment
Author: Baris Ozmen
Author-email: hbaristr@gmail.com
License: BSD
Download-URL: https://github.com/barisozmen/deepaugment/tarball/1.1.2
Platform: UNKNOWN
Classifier: Development Status :: 3 - Alpha
Classifier: Intended Audience :: Developers
Classifier: Programming Language :: Python :: 3
Requires-Dist: matplotlib (==3.0.2)
Requires-Dist: tensorflow (==1.12.0)
Requires-Dist: keras (==2.2.4)
Requires-Dist: imgaug (==0.2.7)
Requires-Dist: setuptools (==40.6.3)
Requires-Dist: keras-applications (==1.0.6)
Requires-Dist: pandas (==0.23.4)
Requires-Dist: scikit-optimize (==0.5.2)
Requires-Dist: click (==7.0)
Requires-Dist: numpy (==1.15.4)
Requires-Dist: opencv-contrib-python
